setup.py
tsf_model/__init__.py
tsf_model/predictor.py
tsf_model.egg-info/PKG-INFO
tsf_model.egg-info/SOURCES.txt
tsf_model.egg-info/dependency_links.txt
tsf_model.egg-info/requires.txt
tsf_model.egg-info/top_level.txt